psc_3d/__init__.py
psc_3d/__main__.py
psc_3d/cli_parser.py
psc_3d/data.json
psc_3d/entry.py
psc_3d/main.py
psc_3d/version.py
psc_3d/scripts/entry.bat
psc_3d/scripts/instalation.bat
psc_3d/scripts/main.bat
psc_3d-1.9.14.dist-info/METADATA
psc_3d-1.9.14.dist-info/WHEEL
psc_3d-1.9.14.dist-info/top_level.txt
psc_3d-1.9.14.dist-info/RECORD
