Metadata-Version: 2.1
Name: psc-3d
Version: 1.9.14
Summary: # Solubility Calculator (Version: 1.9.14)
Home-page: UNKNOWN
Author: Ronald Oguz
Author-email: 
License: UNKNOWN
Platform: UNKNOWN
Requires-Dist: matplotlib
Requires-Dist: numpy
Requires-Dist: rich
